adafruit_bme280/__init__.py
adafruit_bme280/advanced.py
adafruit_bme280/basic.py
adafruit_bme280/protocol.py
adafruit_circuitpython_bme280-2.6.26.dist-info/LICENSE
adafruit_circuitpython_bme280-2.6.26.dist-info/METADATA
adafruit_circuitpython_bme280-2.6.26.dist-info/WHEEL
adafruit_circuitpython_bme280-2.6.26.dist-info/top_level.txt
adafruit_circuitpython_bme280-2.6.26.dist-info/RECORD
